mrai/__init__.py
mrai/help.py
mrai/mrai.py
mrai-1.0.dist-info/METADATA
mrai-1.0.dist-info/WHEEL
mrai-1.0.dist-info/top_level.txt
mrai-1.0.dist-info/RECORD
